opentracing_prometheus/__init__.py
opentracing_prometheus/metrics.py
opentracing_prometheus/tracing.py
opentracing_prometheus-0.1.5.dist-info/DESCRIPTION.rst
opentracing_prometheus-0.1.5.dist-info/METADATA
opentracing_prometheus-0.1.5.dist-info/RECORD
opentracing_prometheus-0.1.5.dist-info/WHEEL
opentracing_prometheus-0.1.5.dist-info/metadata.json
opentracing_prometheus-0.1.5.dist-info/top_level.txt
