Metadata-Version: 2.0
Name: opentracing-prometheus
Version: 0.1.5
Summary: OpenTracing Jaeger and Prometheus integration
Home-page: https://github.com/casualjim/python-opentracing-prometheus
Author: Ivan Porto Carrero
Author-email: UNKNOWN
License: MIT
Keywords: opentracing jaeger prometheus
Platform: any
Classifier: Development Status :: 3 - Alpha
Classifier: License :: OSI Approved :: MIT License
Classifier: Programming Language :: Python :: 2.7
Classifier: Topic :: System :: Monitoring
Requires-Dist: opentracing-instrumentation
Requires-Dist: jaeger-client
Requires-Dist: prometheus-client
